sweet_tea/__init__.py
sweet_tea/abstract_factory.py
sweet_tea/abstract_inverter_factory.py
sweet_tea/base_factory.py
sweet_tea/entry.py
sweet_tea/factory.py
sweet_tea/inverter_factory.py
sweet_tea/registry.py
sweet_tea/singleton_factory.py
sweet_tea/sweet_tea_error.py
sweet_tea/sweet_tea_warning.py
sweet_tea-0.1.38.dist-info/METADATA
sweet_tea-0.1.38.dist-info/WHEEL
sweet_tea-0.1.38.dist-info/licenses/LICENSE
sweet_tea-0.1.38.dist-info/RECORD
