Metadata-Version: 2.4
Name: sweet_tea
Version: 0.1.38
Summary: A comprehensive Python factory pattern implementation with thread-safe operations and type-safe generics
Project-URL: Homepage, https://snoodleboot-io.github.io/sweet_tea/
Project-URL: Documentation, https://snoodleboot-io.github.io/sweet_tea/
Project-URL: Repository, https://github.com/snoodleboot-io/sweet_tea
Project-URL: Issues, https://github.com/snoodleboot-io/sweet_tea/issues
Project-URL: Changelog, https://github.com/snoodleboot-io/sweet_tea/blob/main/CHANGELOG.md
Author-email: "snoodleboot, LLC" <info@snoodleboot.io>
Maintainer-email: "snoodleboot, LLC" <info@snoodleboot.io>
License: Apache-2.0
License-File: LICENSE
Keywords: dependency-injection,factory,patterns,thread-safe,type-safe
Classifier: Development Status :: 4 - Beta
Classifier: Intended Audience :: Developers
Classifier: License :: OSI Approved :: Apache Software License
Classifier: Operating System :: OS Independent
Classifier: Programming Language :: Python :: 3
Classifier: Programming Language :: Python :: 3.10
Classifier: Programming Language :: Python :: 3.11
Classifier: Programming Language :: Python :: 3.12
Classifier: Programming Language :: Python :: 3.13
Classifier: Programming Language :: Python :: Implementation :: CPython
Classifier: Topic :: Software Development :: Libraries :: Python Modules
Classifier: Typing :: Typed
Requires-Python: >=3.10
Requires-Dist: pydantic>=2.12.5
